xug/__init__.py
xug/aes_navicate/__init__.py
xug/aes_navicate/_aes.py
xug/cv/__init__.py
xug/cv/_match.py
xug/gitee/__init__.py
xug/gitee/_gitee.py
xug/list/__init__.py
xug/redwar/__init__.py
xug/redwar/_utils.py
xug/scaling/__init__.py
xug/scaling/_scaling.py
xug-1.0.0.dist-info/METADATA
xug-1.0.0.dist-info/WHEEL
xug-1.0.0.dist-info/top_level.txt
xug-1.0.0.dist-info/RECORD
