Metadata-Version: 2.1
Name: xug
Version: 1.0.0
Requires-Dist: pywin32
Requires-Dist: cryptography
Requires-Dist: requests
Requires-Dist: tqdm
Requires-Dist: pyautogui
Requires-Dist: numpy
Requires-Dist: opencv-python
Requires-Dist: openpyxl
Requires-Dist: pandas
